setup.cfg
setup.py
sk_commonutils/__init__.py
sk_commonutils/logger.py
sk_commonutils.egg-info/PKG-INFO
sk_commonutils.egg-info/SOURCES.txt
sk_commonutils.egg-info/dependency_links.txt
sk_commonutils.egg-info/not-zip-safe
sk_commonutils.egg-info/top_level.txt