Metadata-Version: 1.0
Name: sk-commonutils
Version: 0.2
Summary: Simple Logging Utility
Home-page: UNKNOWN
Author: UNKNOWN
Author-email: sk.karthik315@gmail.com
License: UNKNOWN
Platform: UNKNOWN
